{
  "meta": {
    "timestamp": "2026-03-01T23:19:53.025099Z",
    "agent_status": "REASONING",
    "context_window_hours": 8,
    "total_events_tracked": 50,
    "system_status": "DEMO",
    "sync_timestamp": "2026-03-01T23:19:53.025112Z"
  },
  "data_sources": {
    "polymarket": {
      "type": "DEMO",
      "source": "\u6a21\u62df Polymarket API",
      "last_update": "2026-03-01T23:19:53.025115Z",
      "status": "active"
    },
    "x_intelligence": {
      "type": "DEMO",
      "source": "\u6a21\u62df X/Twitter API",
      "last_update": "2026-03-01T23:19:53.025116Z",
      "status": "active"
    },
    "nautilus": {
      "type": "DEMO",
      "source": "\u6a21\u62df Nautilus Trader",
      "last_update": "2026-03-01T23:19:53.025117Z",
      "status": "active"
    }
  },
  "agent_thoughts": [
    {
      "id": "thought_1772407193",
      "timestamp": "2026-03-01T23:19:53.025121Z",
      "type": "TRIANGULATION",
      "reasoning": "Demo mode: Analyzing market signals with 68% confidence. Polymarket shows bullish trend (+0.8% 1h), X sentiment 0.86, Nautilus signal 0.31.",
      "inputs": {
        "weights": {
          "polymarket": 0.34,
          "x_sentiment": 0.21,
          "nautilus": 0.45
        },
        "action": "BUY"
      },
      "confidence": 0.68,
      "human_feedback": null
    }
  ],
  "triangulation_matrix": {
    "polymarket_x_correlation": 0.86,
    "polymarket_nautilus_correlation": 0.52,
    "x_nautilus_correlation": 0.75,
    "overall_alignment": 0.71,
    "interpretation": "MODERATE_BULLISH"
  },
  "perception": {
    "polymarket": {
      "event": "BTC Price Prediction Market",
      "current_odds": 0.49,
      "delta_1h": 0.008,
      "delta_24h": 0.143,
      "volume_24h": 1700901,
      "liquidity": 2796398,
      "last_trade": "2026-03-01T23:19:53.025136Z",
      "history": [
        {
          "timestamp": "2026-03-01T23:19:53.025137Z",
          "odds": 0.49
        }
      ]
    },
    "x_intelligence": [
      {
        "id": "tweet_demo_1772407193",
        "handle": "@crypto_analyst",
        "content": "Market showing bullish signals. Volume increasing at $42k level. #Crypto",
        "timestamp": "2026-03-01T23:19:53.025143Z",
        "sentiment": "BULLISH",
        "sentiment_score": 0.86,
        "agent_relevance_score": 0.79,
        "extracted_entities": [
          "BTC",
          "resistance",
          "momentum"
        ],
        "impact_score": 8.6,
        "follower_count": 181856
      }
    ],
    "nautilus": {
      "strategy": "Keltner Channel Breakout",
      "position": "FLAT",
      "signal_strength": 0.31,
      "entry_price": 42012.18,
      "current_price": 42427.42,
      "unrealized_pnl": 415.24,
      "daily_pnl": 1803.38,
      "position_size": 1.0,
      "status": "IDLE",
      "indicators": {
        "keltner_upper": 43027.42,
        "keltner_middle": 42427.42,
        "keltner_lower": 41827.42,
        "atr": 373.78,
        "trend": "BEARISH"
      }
    }
  },
  "execution": {
    "current_proposal": {
      "id": "prop_1772407193",
      "action": "BUY",
      "asset": "BTC",
      "reasoning": "Market analysis: Polymarket odds at 0.49 (+0.8% 1h), X sentiment bullish (0.86), Nautilus flat signal (0.31). Risk-adjusted confidence: 68%.",
      "risk_level": "LOW",
      "expected_return": 0.016,
      "confidence": 0.68,
      "status": "PENDING_APPROVAL",
      "created_at": "2026-03-01T23:19:53.025164Z",
      "human_decision": null
    },
    "proposal_history": []
  },
  "context_memory": {
    "events": [
      {
        "id": "evt_0",
        "timestamp": "2026-03-01T23:19:53.025168Z",
        "type": "X_SENTIMENT_SHIFT",
        "description": "Market event 0: Signal detected",
        "relevance_decay": 1.0,
        "impact": "HIGH"
      },
      {
        "id": "evt_1",
        "timestamp": "2026-03-01T23:04:53.025176Z",
        "type": "POLYMARKET_ODDS_CHANGE",
        "description": "Market event 1: Signal detected",
        "relevance_decay": 0.9,
        "impact": "HIGH"
      },
      {
        "id": "evt_2",
        "timestamp": "2026-03-01T22:49:53.025181Z",
        "type": "NAUTILUS_SIGNAL",
        "description": "Market event 2: Signal detected",
        "relevance_decay": 0.8,
        "impact": "HIGH"
      },
      {
        "id": "evt_3",
        "timestamp": "2026-03-01T22:34:53.025186Z",
        "type": "X_SENTIMENT_SHIFT",
        "description": "Market event 3: Signal detected",
        "relevance_decay": 0.7,
        "impact": "MEDIUM"
      },
      {
        "id": "evt_4",
        "timestamp": "2026-03-01T22:19:53.025189Z",
        "type": "POLYMARKET_ODDS_CHANGE",
        "description": "Market event 4: Signal detected",
        "relevance_decay": 0.6,
        "impact": "MEDIUM"
      },
      {
        "id": "evt_5",
        "timestamp": "2026-03-01T22:04:53.025192Z",
        "type": "NAUTILUS_SIGNAL",
        "description": "Market event 5: Signal detected",
        "relevance_decay": 0.5,
        "impact": "MEDIUM"
      },
      {
        "id": "evt_6",
        "timestamp": "2026-03-01T21:49:53.025195Z",
        "type": "X_SENTIMENT_SHIFT",
        "description": "Market event 6: Signal detected",
        "relevance_decay": 0.4,
        "impact": "LOW"
      },
      {
        "id": "evt_7",
        "timestamp": "2026-03-01T21:34:53.025203Z",
        "type": "POLYMARKET_ODDS_CHANGE",
        "description": "Market event 7: Signal detected",
        "relevance_decay": 0.3,
        "impact": "LOW"
      }
    ]
  },
  "github_actions": {
    "last_run": "2026-03-01T23:19:53.025207Z",
    "status": "success",
    "workflow": "update-data",
    "duration_seconds": 13,
    "next_run": "2026-03-01T23:24:53.025210Z"
  }
}